token_status_list-0.1.0a2.dev1.dist-info/METADATA
token_status_list-0.1.0a2.dev1.dist-info/WHEEL
token_status_list-0.1.0a2.dev1.dist-info/entry_points.txt
token_status_list-0.1.0a2.dev1.dist-info/licenses/LICENSE
token_status_list.py
token_status_list-0.1.0a2.dev1.dist-info/RECORD
