Metadata-Version: 2.1
Name: token-status-list
Version: 0.1.0a2.dev1
Summary: Implementation of IETF Token Status List
Author-Email: Daniel Bluhm <dbluhm@pm.me>
License: Apache-2.0
Requires-Python: >=3.10
Provides-Extra: cbor
Requires-Dist: cbor2>=5.6.4; extra == "cbor"
